LICENSE
MANIFEST.in
README.md
setup.py
Jedutils.egg-info/PKG-INFO
Jedutils.egg-info/SOURCES.txt
Jedutils.egg-info/dependency_links.txt
Jedutils.egg-info/requires.txt
Jedutils.egg-info/top_level.txt
jedutils/__init__.py
jedutils/asyncio/__init__.py
jedutils/asyncio/_async_redis_pipe.py
jedutils/asyncio/_concurrency_manager.py
jedutils/asyncio/_run_async.py
jedutils/asyncio/_rwlock.py
jedutils/asyncio/network/__init__.py
jedutils/asyncio/network/_dl.py
jedutils/base62/__init__.py
jedutils/base62/b62.py
jedutils/databases/__init__.py
jedutils/databases/_in_memory.py
jedutils/math/__init__.py
jedutils/math/_number_formatter.py
jedutils/strings/__init__.py
jedutils/strings/_chunked_text.py
jedutils/strings/_numerals.py
jedutils/strings/_random_string.py
jedutils/tdlib/__init__.py
jedutils/tdlib/arithmetic.py