Metadata-Version: 2.4
Name: Jedutils
Version: 0.2.7
Summary: Jedutils is a Python utilities package that provides a collection of useful helper functions.
Home-page: https://github.com/AYMENJD/jedutils
Author: AYMEN Mohammed
Author-email: let.me.code.safe@gmail.com
License: MIT
Project-URL: Source, https://github.com/AYMENJD/jedutils
Project-URL: Tracker, https://github.com/AYMENJD/jedutils/issues
Keywords: utilities,tools,library,helper,functions,development
License-File: LICENSE
Provides-Extra: all
Requires-Dist: redis; extra == "all"
Requires-Dist: aiohttp; extra == "all"
Dynamic: author
Dynamic: author-email
Dynamic: description
Dynamic: description-content-type
Dynamic: home-page
Dynamic: keywords
Dynamic: license
Dynamic: license-file
Dynamic: project-url
Dynamic: provides-extra
Dynamic: summary
